canine/__init__.py
canine/__main__.py
canine/orchestrator.py
canine/utils.py
canine/xargs.py
canine/adapters/__init__.py
canine/adapters/base.py
canine/adapters/firecloud.py
canine/backends/__init__.py
canine/backends/base.py
canine/backends/dockerTransient.py
canine/backends/gcpTransient.py
canine/backends/imageTransient.py
canine/backends/local.py
canine/backends/remote.py
canine/backends/dummy/Dockerfile
canine/backends/dummy/__init__.py
canine/backends/dummy/controller.py
canine/backends/dummy/docker
canine/backends/dummy/worker.sh
canine/backends/dummy/conf/slurm.conf
canine/backends/dummy/conf/slurmdbd.conf
canine/backends/slurm-docker/src/Dockerfile
canine/backends/slurm-docker/src/container_host_image_startup_script.sh
canine/backends/slurm-docker/src/docker_build.sh
canine/backends/slurm-docker/src/docker_entrypoint_controller.sh
canine/backends/slurm-docker/src/docker_entrypoint_worker.sh
canine/backends/slurm-docker/src/docker_run.sh
canine/backends/slurm-docker/src/generate_base_image.sh
canine/backends/slurm-docker/src/generate_container_host_image.sh
canine/backends/slurm-docker/src/nfs_provision_server.sh
canine/backends/slurm-docker/src/nfs_provision_worker.sh
canine/backends/slurm-docker/src/provision_server.py
canine/backends/slurm-docker/src/provision_storage.sh
canine/backends/slurm-docker/src/provision_storage_container_host.sh
canine/backends/slurm-docker/src/provision_worker.sh
canine/backends/slurm-docker/src/provision_worker_container_host.sh
canine/backends/slurm-docker/src/setup.sh
canine/backends/slurm-docker/src/slurm_resume.py
canine/backends/slurm-docker/src/slurm_resume.sh
canine/backends/slurm-docker/src/slurm_resume_wrapper.sh
canine/backends/slurm-docker/src/slurm_start.sh
canine/backends/slurm-docker/src/slurm_suspend.sh
canine/backends/slurm-docker/src/slurm_suspend_wrapper.sh
canine/backends/slurm-gcp/CONTRIBUTING.md
canine/backends/slurm-gcp/LICENSE
canine/backends/slurm-gcp/README.md
canine-0.9.0.dist-info/LICENSE
canine-0.9.0.dist-info/METADATA
canine-0.9.0.dist-info/WHEEL
canine-0.9.0.dist-info/entry_points.txt
canine-0.9.0.dist-info/top_level.txt
canine-0.9.0.dist-info/RECORD
