Metadata-Version: 2.1
Name: canine
Version: 0.9.0
Summary: A modular, high-performance computing solution to run jobs using SLURM
Home-page: https://github.com/broadinstitute/canine
Author: Aaron Graubert - Broad Institute - Cancer Genome Computational Analysis
Author-email: aarong@broadinstitute.org
License: BSD3
Platform: UNKNOWN
Classifier: Development Status :: 4 - Beta
Classifier: Programming Language :: Python :: 3
Classifier: Intended Audience :: Science/Research
Classifier: Topic :: Scientific/Engineering :: Bio-Informatics
Classifier: Topic :: System :: Clustering
Classifier: Topic :: System :: Distributed Computing
Classifier: Typing :: Typed
Classifier: License :: OSI Approved :: BSD License
Requires-Dist: paramiko (>=2.5.0)
Requires-Dist: pandas (>=0.24.1)
Requires-Dist: google-auth (>=1.6.3)
Requires-Dist: PyYAML (>=5.1)
Requires-Dist: agutil (>=4.1.0)
Requires-Dist: hound (>=0.2.0)
Requires-Dist: firecloud-dalmatian (>=0.0.17)
Requires-Dist: google-api-python-client (>=1.7.11)
Requires-Dist: docker (>=4.1.0)
Requires-Dist: psutil (>=5.6.7)
Requires-Dist: port-for (>=0.4)
Requires-Dist: tables (>=3.6.1)
